README.md
setup.py
lhe2sqlite/__init__.py
lhe2sqlite.egg-info/PKG-INFO
lhe2sqlite.egg-info/SOURCES.txt
lhe2sqlite.egg-info/dependency_links.txt
lhe2sqlite.egg-info/top_level.txt
scripts/convertlhe2sqlite